[
    {
        "%vlocity_namespace%__DefaultValue__c": "Siebel Hierarchical",
        "%vlocity_namespace%__DomainObjectAPIName__c": "json",
        "%vlocity_namespace%__DomainObjectCreationOrder__c": 1,
        "%vlocity_namespace%__DomainObjectFieldAPIName__c": "SiebelMessage:@IntObjectFormat",
        "%vlocity_namespace%__FormulaOrder__c": 0,
        "%vlocity_namespace%__GlobalKey__c": "46cf1f75-f704-955e-40ec-c4460dabcf57",
        "%vlocity_namespace%__InterfaceObjectName__c": "json",
        "%vlocity_namespace%__IsDisabled__c": false,
        "%vlocity_namespace%__IsRequiredForUpsert__c": false,
        "%vlocity_namespace%__LinkCreatedIndex__c": 0,
        "%vlocity_namespace%__MapId__c": "AssetRequestBodyCustom8351",
        "%vlocity_namespace%__UpsertKey__c": false,
        "Name": "AssetRequestBody",
        "VlocityDataPackType": "SObject",
        "VlocityRecordSObjectType": "%vlocity_namespace%__DRMapItem__c"
    },
    {
        "%vlocity_namespace%__DefaultValue__c": "Asset Management",
        "%vlocity_namespace%__DomainObjectAPIName__c": "json",
        "%vlocity_namespace%__DomainObjectCreationOrder__c": 1,
        "%vlocity_namespace%__DomainObjectFieldAPIName__c": "SiebelMessage:@IntObjectName",
        "%vlocity_namespace%__FormulaOrder__c": 0,
        "%vlocity_namespace%__GlobalKey__c": "38ec91cb-1c66-558a-2c6a-8d91d59c9c83",
        "%vlocity_namespace%__InterfaceObjectName__c": "json",
        "%vlocity_namespace%__IsDisabled__c": false,
        "%vlocity_namespace%__IsRequiredForUpsert__c": false,
        "%vlocity_namespace%__LinkCreatedIndex__c": 0,
        "%vlocity_namespace%__MapId__c": "AssetRequestBodyCustom1474",
        "%vlocity_namespace%__UpsertKey__c": false,
        "Name": "AssetRequestBody",
        "VlocityDataPackType": "SObject",
        "VlocityRecordSObjectType": "%vlocity_namespace%__DRMapItem__c"
    },
    {
        "%vlocity_namespace%__DefaultValue__c": "\"\"",
        "%vlocity_namespace%__DomainObjectAPIName__c": "json",
        "%vlocity_namespace%__DomainObjectCreationOrder__c": 1,
        "%vlocity_namespace%__DomainObjectFieldAPIName__c": "SiebelMessage:@MessageId",
        "%vlocity_namespace%__FormulaOrder__c": 0,
        "%vlocity_namespace%__GlobalKey__c": "2a3e13f1-98d5-1f65-19cd-54de5bef15f8",
        "%vlocity_namespace%__InterfaceObjectName__c": "json",
        "%vlocity_namespace%__IsDisabled__c": false,
        "%vlocity_namespace%__IsRequiredForUpsert__c": false,
        "%vlocity_namespace%__LinkCreatedIndex__c": 0,
        "%vlocity_namespace%__MapId__c": "AssetRequestBodyCustom2187",
        "%vlocity_namespace%__UpsertKey__c": false,
        "Name": "AssetRequestBody",
        "VlocityDataPackType": "SObject",
        "VlocityRecordSObjectType": "%vlocity_namespace%__DRMapItem__c"
    },
    {
        "%vlocity_namespace%__DefaultValue__c": "Integration Object",
        "%vlocity_namespace%__DomainObjectAPIName__c": "json",
        "%vlocity_namespace%__DomainObjectCreationOrder__c": 1,
        "%vlocity_namespace%__DomainObjectFieldAPIName__c": "SiebelMessage:@MessageType",
        "%vlocity_namespace%__FormulaOrder__c": 0,
        "%vlocity_namespace%__GlobalKey__c": "02ca9e1b-9d96-35de-35c9-92f4a4b65c12",
        "%vlocity_namespace%__InterfaceObjectName__c": "json",
        "%vlocity_namespace%__IsDisabled__c": false,
        "%vlocity_namespace%__IsRequiredForUpsert__c": false,
        "%vlocity_namespace%__LinkCreatedIndex__c": 0,
        "%vlocity_namespace%__MapId__c": "AssetRequestBodyCustom2597",
        "%vlocity_namespace%__UpsertKey__c": false,
        "Name": "AssetRequestBody",
        "VlocityDataPackType": "SObject",
        "VlocityRecordSObjectType": "%vlocity_namespace%__DRMapItem__c"
    },
    {
        "%vlocity_namespace%__DomainObjectAPIName__c": "json",
        "%vlocity_namespace%__DomainObjectCreationOrder__c": 1,
        "%vlocity_namespace%__DomainObjectFieldAPIName__c": "SiebelMessage:ListOfAsset_Management_Io:AssetMgmt-Asset:BillingAccount:#text",
        "%vlocity_namespace%__FormulaOrder__c": 0,
        "%vlocity_namespace%__GlobalKey__c": "e85bdb9f-ff3e-990e-cb83-09531a318c66",
        "%vlocity_namespace%__InterfaceFieldAPIName__c": "SiebelMessage:ListOfAccount:Account:Name:#text",
        "%vlocity_namespace%__InterfaceObjectName__c": "json",
        "%vlocity_namespace%__IsDisabled__c": false,
        "%vlocity_namespace%__IsRequiredForUpsert__c": false,
        "%vlocity_namespace%__LinkCreatedIndex__c": 0,
        "%vlocity_namespace%__MapId__c": "AssetRequestBodyCustom8321",
        "%vlocity_namespace%__UpsertKey__c": false,
        "Name": "AssetRequestBody",
        "VlocityDataPackType": "SObject",
        "VlocityRecordSObjectType": "%vlocity_namespace%__DRMapItem__c"
    }
]