[
    {
        "%vlocity_namespace%__AddDate__c": "",
        "%vlocity_namespace%__AttributeAdjustmentComments__c": "",
        "%vlocity_namespace%__AttributeAdjustmentUnits__c": "",
        "%vlocity_namespace%__AttributeCategoryId__c": {
            "%vlocity_namespace%__Code__c": "VLO-PRO-0006",
            "VlocityDataPackType": "VlocityLookupMatchingKeyObject",
            "VlocityLookupRecordSourceKey": "%vlocity_namespace%__AttributeCategory__c/VLO-PRO-0006",
            "VlocityRecordSObjectType": "%vlocity_namespace%__AttributeCategory__c"
        },
        "%vlocity_namespace%__AttributeDisplayNameOverride__c": "",
        "%vlocity_namespace%__AttributeDisplaySequence__c": "4",
        "%vlocity_namespace%__AttributeId__c": {
            "%vlocity_namespace%__Code__c": "ATTRIBUTE-089",
            "VlocityDataPackType": "VlocityLookupMatchingKeyObject",
            "VlocityLookupRecordSourceKey": "%vlocity_namespace%__Attribute__c/ATTRIBUTE-089",
            "VlocityRecordSObjectType": "%vlocity_namespace%__Attribute__c"
        },
        "%vlocity_namespace%__AttributeId__r.%vlocity_namespace%__Code__c": "ATTRIBUTE-089",
        "%vlocity_namespace%__ConfigurationDetail__c": "",
        "%vlocity_namespace%__ConfigurationStages__c": "",
        "%vlocity_namespace%__CustomConfigUiTemplate__c": "",
        "%vlocity_namespace%__Data__c": "",
        "%vlocity_namespace%__DefaultPicklistEntryId__c": "",
        "%vlocity_namespace%__DefaultPicklistValueId__c": "",
        "%vlocity_namespace%__DisplaySequence__c": "14",
        "%vlocity_namespace%__EndStory__c": "",
        "%vlocity_namespace%__ExcludedPicklistEntryIds__c": "",
        "%vlocity_namespace%__ExcludedPicklistValues__c": "",
        "%vlocity_namespace%__FormatMask__c": "",
        "%vlocity_namespace%__GlobalKey__c": "fa0e5bd9-2277-b245-d819-9ae031b4bb11",
        "%vlocity_namespace%__HasRule__c": false,
        "%vlocity_namespace%__HelpText__c": "",
        "%vlocity_namespace%__IsActiveAssignment__c": false,
        "%vlocity_namespace%__IsActive__c": true,
        "%vlocity_namespace%__IsConfigurable__c": true,
        "%vlocity_namespace%__IsDynamic__c": false,
        "%vlocity_namespace%__IsEncrypted__c": false,
        "%vlocity_namespace%__IsHidden__c": false,
        "%vlocity_namespace%__IsNotAssetizable__c": false,
        "%vlocity_namespace%__IsNotTranslatable__c": false,
        "%vlocity_namespace%__IsOverride__c": false,
        "%vlocity_namespace%__IsQueryDriven__c": false,
        "%vlocity_namespace%__IsReadOnly__c": false,
        "%vlocity_namespace%__IsRequired__c": false,
        "%vlocity_namespace%__LookupFilter__c": "",
        "%vlocity_namespace%__LookupObjectId__c": "",
        "%vlocity_namespace%__LookupObjectTypeId__c": "",
        "%vlocity_namespace%__ObjectId__c": {
            "%vlocity_namespace%__GlobalKey__c": "74854338-30f8-dc88-1029-951f08a94e08",
            "VlocityDataPackType": "VlocityMatchingKeyObject",
            "VlocityMatchingRecordSourceKey": "Product2/74854338-30f8-dc88-1029-951f08a94e08",
            "VlocityRecordSObjectType": "Product2"
        },
        "%vlocity_namespace%__ObjectType__c": "Product2",
        "%vlocity_namespace%__PicklistId__c": "",
        "%vlocity_namespace%__QueryCode__c": "",
        "%vlocity_namespace%__QueryLabel__c": "",
        "%vlocity_namespace%__RemoveDate__c": "",
        "%vlocity_namespace%__RemovedFlag__c": false,
        "%vlocity_namespace%__RuleData__c": "",
        "%vlocity_namespace%__RuleMessage__c": "",
        "%vlocity_namespace%__StartStory__c": "",
        "%vlocity_namespace%__StyleClass__c": "",
        "%vlocity_namespace%__UIDisplayType__c": "Dropdown",
        "%vlocity_namespace%__ValidValuesData__c": [
            {
                "displayText": "100MB",
                "id": 1,
                "isDefault": true,
                "isEditable": false,
                "value": "100MB"
            },
            {
                "displayText": "500MB",
                "id": 2,
                "isDefault": false,
                "isEditable": false,
                "value": "500MB"
            },
            {
                "displayText": "1GB",
                "id": 3,
                "isDefault": false,
                "isEditable": false,
                "value": "1GB"
            },
            {
                "displayText": "5GB",
                "id": 4,
                "isDefault": false,
                "isEditable": false,
                "value": "5GB"
            },
            {
                "displayText": "10GB",
                "id": 5,
                "isDefault": false,
                "isEditable": true,
                "value": "10GB"
            }
        ],
        "%vlocity_namespace%__ValueDataType__c": "Picklist",
        "%vlocity_namespace%__ValueDecoder__c": "",
        "%vlocity_namespace%__ValueDescription__c": "The storage space for the service.",
        "%vlocity_namespace%__Value__c": "",
        "Name": "ATTRIBUTE-089",
        "VlocityDataPackType": "SObject",
        "VlocityRecordSObjectType": "%vlocity_namespace%__AttributeAssignment__c",
        "VlocityRecordSourceKey": "%vlocity_namespace%__AttributeAssignment__c/%vlocity_namespace%__Attribute__c/ATTRIBUTE-089/Product2/74854338-30f8-dc88-1029-951f08a94e08/GlobalKey/fa0e5bd9-2277-b245-d819-9ae031b4bb11"
    },
    {
        "%vlocity_namespace%__AddDate__c": "",
        "%vlocity_namespace%__AttributeAdjustmentComments__c": "",
        "%vlocity_namespace%__AttributeAdjustmentUnits__c": "",
        "%vlocity_namespace%__AttributeCategoryId__c": {
            "%vlocity_namespace%__Code__c": "VLO-PRO-0006",
            "VlocityDataPackType": "VlocityLookupMatchingKeyObject",
            "VlocityLookupRecordSourceKey": "%vlocity_namespace%__AttributeCategory__c/VLO-PRO-0006",
            "VlocityRecordSObjectType": "%vlocity_namespace%__AttributeCategory__c"
        },
        "%vlocity_namespace%__AttributeDisplayNameOverride__c": "",
        "%vlocity_namespace%__AttributeDisplaySequence__c": "5",
        "%vlocity_namespace%__AttributeId__c": {
            "%vlocity_namespace%__Code__c": "ATTRIBUTE-090",
            "VlocityDataPackType": "VlocityLookupMatchingKeyObject",
            "VlocityLookupRecordSourceKey": "%vlocity_namespace%__Attribute__c/ATTRIBUTE-090",
            "VlocityRecordSObjectType": "%vlocity_namespace%__Attribute__c"
        },
        "%vlocity_namespace%__AttributeId__r.%vlocity_namespace%__Code__c": "ATTRIBUTE-090",
        "%vlocity_namespace%__ConfigurationDetail__c": "",
        "%vlocity_namespace%__ConfigurationStages__c": "",
        "%vlocity_namespace%__CustomConfigUiTemplate__c": "",
        "%vlocity_namespace%__Data__c": "",
        "%vlocity_namespace%__DefaultPicklistEntryId__c": "",
        "%vlocity_namespace%__DefaultPicklistValueId__c": "",
        "%vlocity_namespace%__DisplaySequence__c": "14",
        "%vlocity_namespace%__EndStory__c": "",
        "%vlocity_namespace%__ExcludedPicklistEntryIds__c": "",
        "%vlocity_namespace%__ExcludedPicklistValues__c": "",
        "%vlocity_namespace%__FormatMask__c": "",
        "%vlocity_namespace%__GlobalKey__c": "c68ec0ef-fcec-6e98-d964-10fa00eb3e9b",
        "%vlocity_namespace%__HasRule__c": false,
        "%vlocity_namespace%__HelpText__c": "",
        "%vlocity_namespace%__IsActiveAssignment__c": false,
        "%vlocity_namespace%__IsActive__c": true,
        "%vlocity_namespace%__IsConfigurable__c": true,
        "%vlocity_namespace%__IsDynamic__c": false,
        "%vlocity_namespace%__IsEncrypted__c": false,
        "%vlocity_namespace%__IsHidden__c": false,
        "%vlocity_namespace%__IsNotAssetizable__c": false,
        "%vlocity_namespace%__IsNotTranslatable__c": false,
        "%vlocity_namespace%__IsOverride__c": false,
        "%vlocity_namespace%__IsQueryDriven__c": false,
        "%vlocity_namespace%__IsReadOnly__c": false,
        "%vlocity_namespace%__IsRequired__c": false,
        "%vlocity_namespace%__LookupFilter__c": "",
        "%vlocity_namespace%__LookupObjectId__c": "",
        "%vlocity_namespace%__LookupObjectTypeId__c": "",
        "%vlocity_namespace%__ObjectId__c": {
            "%vlocity_namespace%__GlobalKey__c": "74854338-30f8-dc88-1029-951f08a94e08",
            "VlocityDataPackType": "VlocityMatchingKeyObject",
            "VlocityMatchingRecordSourceKey": "Product2/74854338-30f8-dc88-1029-951f08a94e08",
            "VlocityRecordSObjectType": "Product2"
        },
        "%vlocity_namespace%__ObjectType__c": "Product2",
        "%vlocity_namespace%__PicklistId__c": "",
        "%vlocity_namespace%__QueryCode__c": "",
        "%vlocity_namespace%__QueryLabel__c": "",
        "%vlocity_namespace%__RemoveDate__c": "",
        "%vlocity_namespace%__RemovedFlag__c": false,
        "%vlocity_namespace%__RuleData__c": "",
        "%vlocity_namespace%__RuleMessage__c": "",
        "%vlocity_namespace%__StartStory__c": "",
        "%vlocity_namespace%__StyleClass__c": "",
        "%vlocity_namespace%__UIDisplayType__c": "Dropdown",
        "%vlocity_namespace%__ValidValuesData__c": [
            {
                "displayText": "10GB",
                "id": 1,
                "isDefault": true,
                "isEditable": false,
                "value": "10GB"
            },
            {
                "displayText": "25GB",
                "id": 2,
                "isDefault": false,
                "isEditable": false,
                "value": "25GB"
            },
            {
                "displayText": "50GB",
                "id": 3,
                "isDefault": false,
                "isEditable": false,
                "value": "50GB"
            },
            {
                "displayText": "100GB",
                "id": 4,
                "isDefault": false,
                "isEditable": true,
                "value": "100GB"
            }
        ],
        "%vlocity_namespace%__ValueDataType__c": "Picklist",
        "%vlocity_namespace%__ValueDecoder__c": "",
        "%vlocity_namespace%__ValueDescription__c": "The monthly bandwidth limit for the service.",
        "%vlocity_namespace%__Value__c": "",
        "Name": "ATTRIBUTE-090",
        "VlocityDataPackType": "SObject",
        "VlocityRecordSObjectType": "%vlocity_namespace%__AttributeAssignment__c",
        "VlocityRecordSourceKey": "%vlocity_namespace%__AttributeAssignment__c/%vlocity_namespace%__Attribute__c/ATTRIBUTE-090/Product2/74854338-30f8-dc88-1029-951f08a94e08/GlobalKey/c68ec0ef-fcec-6e98-d964-10fa00eb3e9b"
    },
    {
        "%vlocity_namespace%__AddDate__c": "",
        "%vlocity_namespace%__AttributeAdjustmentComments__c": "",
        "%vlocity_namespace%__AttributeAdjustmentUnits__c": "",
        "%vlocity_namespace%__AttributeCategoryId__c": {
            "%vlocity_namespace%__Code__c": "VLO-PRO-0015",
            "VlocityDataPackType": "VlocityLookupMatchingKeyObject",
            "VlocityLookupRecordSourceKey": "%vlocity_namespace%__AttributeCategory__c/VLO-PRO-0015",
            "VlocityRecordSObjectType": "%vlocity_namespace%__AttributeCategory__c"
        },
        "%vlocity_namespace%__AttributeDisplayNameOverride__c": "Provider",
        "%vlocity_namespace%__AttributeDisplaySequence__c": "4",
        "%vlocity_namespace%__AttributeId__c": {
            "%vlocity_namespace%__Code__c": "ATTRIBUTE-124",
            "VlocityDataPackType": "VlocityLookupMatchingKeyObject",
            "VlocityLookupRecordSourceKey": "%vlocity_namespace%__Attribute__c/ATTRIBUTE-124",
            "VlocityRecordSObjectType": "%vlocity_namespace%__Attribute__c"
        },
        "%vlocity_namespace%__AttributeId__r.%vlocity_namespace%__Code__c": "ATTRIBUTE-124",
        "%vlocity_namespace%__ConfigurationDetail__c": "",
        "%vlocity_namespace%__ConfigurationStages__c": "",
        "%vlocity_namespace%__CustomConfigUiTemplate__c": "",
        "%vlocity_namespace%__Data__c": "",
        "%vlocity_namespace%__DefaultPicklistEntryId__c": "",
        "%vlocity_namespace%__DefaultPicklistValueId__c": "",
        "%vlocity_namespace%__DisplaySequence__c": "null",
        "%vlocity_namespace%__EndStory__c": "",
        "%vlocity_namespace%__ExcludedPicklistEntryIds__c": "",
        "%vlocity_namespace%__ExcludedPicklistValues__c": "",
        "%vlocity_namespace%__FormatMask__c": "",
        "%vlocity_namespace%__GlobalKey__c": "ddf7350e-6e6c-d194-0343-648425b03b0d",
        "%vlocity_namespace%__HasRule__c": false,
        "%vlocity_namespace%__HelpText__c": "",
        "%vlocity_namespace%__IsActiveAssignment__c": true,
        "%vlocity_namespace%__IsActive__c": true,
        "%vlocity_namespace%__IsConfigurable__c": false,
        "%vlocity_namespace%__IsDynamic__c": false,
        "%vlocity_namespace%__IsEncrypted__c": false,
        "%vlocity_namespace%__IsHidden__c": false,
        "%vlocity_namespace%__IsNotAssetizable__c": false,
        "%vlocity_namespace%__IsNotTranslatable__c": false,
        "%vlocity_namespace%__IsOverride__c": false,
        "%vlocity_namespace%__IsQueryDriven__c": false,
        "%vlocity_namespace%__IsReadOnly__c": false,
        "%vlocity_namespace%__IsRequired__c": false,
        "%vlocity_namespace%__LookupFilter__c": "",
        "%vlocity_namespace%__LookupObjectId__c": "",
        "%vlocity_namespace%__LookupObjectTypeId__c": "",
        "%vlocity_namespace%__ObjectId__c": {
            "%vlocity_namespace%__GlobalKey__c": "74854338-30f8-dc88-1029-951f08a94e08",
            "VlocityDataPackType": "VlocityMatchingKeyObject",
            "VlocityMatchingRecordSourceKey": "Product2/74854338-30f8-dc88-1029-951f08a94e08",
            "VlocityRecordSObjectType": "Product2"
        },
        "%vlocity_namespace%__ObjectType__c": "Product2",
        "%vlocity_namespace%__PicklistId__c": "",
        "%vlocity_namespace%__QueryCode__c": "",
        "%vlocity_namespace%__QueryLabel__c": "",
        "%vlocity_namespace%__RemoveDate__c": "",
        "%vlocity_namespace%__RemovedFlag__c": false,
        "%vlocity_namespace%__RuleData__c": "",
        "%vlocity_namespace%__RuleMessage__c": "",
        "%vlocity_namespace%__StartStory__c": "",
        "%vlocity_namespace%__StyleClass__c": "",
        "%vlocity_namespace%__UIDisplayType__c": "",
        "%vlocity_namespace%__ValidValuesData__c": "",
        "%vlocity_namespace%__ValueDataType__c": "Text",
        "%vlocity_namespace%__ValueDecoder__c": "",
        "%vlocity_namespace%__ValueDescription__c": "",
        "%vlocity_namespace%__Value__c": "",
        "Name": "TempAA-ATTRIBUTE-124",
        "VlocityDataPackType": "SObject",
        "VlocityRecordSObjectType": "%vlocity_namespace%__AttributeAssignment__c",
        "VlocityRecordSourceKey": "%vlocity_namespace%__AttributeAssignment__c/%vlocity_namespace%__Attribute__c/ATTRIBUTE-124/Product2/74854338-30f8-dc88-1029-951f08a94e08/GlobalKey/ddf7350e-6e6c-d194-0343-648425b03b0d"
    }
]