{
    "%vlocity_namespace%__Channel__c": "",
    "%vlocity_namespace%__ContentType__c": "Image",
    "%vlocity_namespace%__Description__c": "The default product image.",
    "%vlocity_namespace%__DisplayConditionsData__c": "",
    "%vlocity_namespace%__GlobalKey__c": "4a273d00-d9c1-37d2-9ff9-b14342e0dabc",
    "%vlocity_namespace%__IsDefaultImage__c": true,
    "%vlocity_namespace%__IsPrivate__c": false,
    "%vlocity_namespace%__ObjectId__c": {
        "%vlocity_namespace%__GlobalKey__c": "c91a6404-d696-8f00-1cb7-493c1d80494c",
        "VlocityDataPackType": "VlocityLookupMatchingKeyObject",
        "VlocityLookupRecordSourceKey": "Product2/c91a6404-d696-8f00-1cb7-493c1d80494c",
        "VlocityRecordSObjectType": "Product2"
    },
    "%vlocity_namespace%__SequenceNumber__c": 1,
    "%vlocity_namespace%__UrlLong__c": "https://vlocitydemodx-cdn.herokuapp.com/content/industry/cmt/VDOProductResources/images/TNHandshake.png",
    "%vlocity_namespace%__Url__c": "",
    "Name": "CloudVoice Collaborative Product Image",
    "VlocityDataPackType": "SObject",
    "VlocityRecordSObjectType": "%vlocity_namespace%__VlocityAttachment__c",
    "VlocityRecordSourceKey": "%vlocity_namespace%__VlocityAttachment__c/4a273d00-d9c1-37d2-9ff9-b14342e0dabc"
}