[
    {
        "%vlocity_namespace%__DomainObjectAPIName__c": "json",
        "%vlocity_namespace%__DomainObjectCreationOrder__c": 0,
        "%vlocity_namespace%__DomainObjectFieldAPIName__c": "Intelligence",
        "%vlocity_namespace%__FilterGroup__c": 0,
        "%vlocity_namespace%__FilterOperator__c": "=",
        "%vlocity_namespace%__FilterValue__c": "Id:IntelligenceId",
        "%vlocity_namespace%__GlobalKey__c": "7878cb23-1fcf-da0b-9197-d248d5920277",
        "%vlocity_namespace%__InterfaceFieldAPIName__c": "Id",
        "%vlocity_namespace%__InterfaceObjectLookupOrder__c": 1,
        "%vlocity_namespace%__InterfaceObjectName__c": "%vlocity_namespace%__VqResource__c",
        "%vlocity_namespace%__IsDisabled__c": false,
        "%vlocity_namespace%__IsRequiredForUpsert__c": false,
        "%vlocity_namespace%__MapId__c": "VPLGetRecommendedProducts-101-1Customa0h6A000001OTxCQAWItem0",
        "%vlocity_namespace%__UpsertKey__c": false,
        "Name": "VPLGetRecommendedProducts-101-1",
        "VlocityDataPackType": "SObject",
        "VlocityRecordSObjectType": "%vlocity_namespace%__DRMapItem__c"
    },
    {
        "%vlocity_namespace%__DomainObjectAPIName__c": "json",
        "%vlocity_namespace%__DomainObjectCreationOrder__c": 0,
        "%vlocity_namespace%__DomainObjectFieldAPIName__c": "Intelligence:Product",
        "%vlocity_namespace%__FilterGroup__c": 0,
        "%vlocity_namespace%__FilterOperator__c": "=",
        "%vlocity_namespace%__FilterValue__c": "Intelligence:%vlocity_namespace%__TargetObjectKey__c",
        "%vlocity_namespace%__GlobalKey__c": "d33dbce0-5799-1e97-2ef8-1d7da4ae2042",
        "%vlocity_namespace%__InterfaceFieldAPIName__c": "Id",
        "%vlocity_namespace%__InterfaceObjectLookupOrder__c": 2,
        "%vlocity_namespace%__InterfaceObjectName__c": "Product2",
        "%vlocity_namespace%__IsDisabled__c": false,
        "%vlocity_namespace%__IsRequiredForUpsert__c": false,
        "%vlocity_namespace%__MapId__c": "VPLGetRecommendedProducts-101-1Customa0h6A000001OTxCQAWItem1",
        "%vlocity_namespace%__UpsertKey__c": false,
        "Name": "VPLGetRecommendedProducts-101-1",
        "VlocityDataPackType": "SObject",
        "VlocityRecordSObjectType": "%vlocity_namespace%__DRMapItem__c"
    },
    {
        "%vlocity_namespace%__DomainObjectAPIName__c": "json",
        "%vlocity_namespace%__DomainObjectCreationOrder__c": 1,
        "%vlocity_namespace%__DomainObjectFieldAPIName__c": "Product:ProductId",
        "%vlocity_namespace%__GlobalKey__c": "9752e16b-5e84-9176-d9fe-af24066b5e6e",
        "%vlocity_namespace%__InterfaceFieldAPIName__c": "Intelligence:%vlocity_namespace%__TargetObjectKey__c",
        "%vlocity_namespace%__IsDisabled__c": false,
        "%vlocity_namespace%__IsRequiredForUpsert__c": false,
        "%vlocity_namespace%__MapId__c": "VPLGetRecommendedProducts-101-1Customa0h6A000001OTxCQAWItem3",
        "%vlocity_namespace%__UpsertKey__c": false,
        "Name": "VPLGetRecommendedProducts-101-1",
        "VlocityDataPackType": "SObject",
        "VlocityRecordSObjectType": "%vlocity_namespace%__DRMapItem__c"
    },
    {
        "%vlocity_namespace%__DomainObjectAPIName__c": "json",
        "%vlocity_namespace%__DomainObjectCreationOrder__c": 1,
        "%vlocity_namespace%__DomainObjectFieldAPIName__c": "Product:ProductName",
        "%vlocity_namespace%__GlobalKey__c": "fcabb890-28b7-fa08-2e0a-0eaf73d24c21",
        "%vlocity_namespace%__InterfaceFieldAPIName__c": "Intelligence:Product:Name",
        "%vlocity_namespace%__IsDisabled__c": false,
        "%vlocity_namespace%__IsRequiredForUpsert__c": false,
        "%vlocity_namespace%__MapId__c": "VPLGetRecommendedProducts-101-1Customa0h6A000001OTxCQAWItem2",
        "%vlocity_namespace%__UpsertKey__c": false,
        "Name": "VPLGetRecommendedProducts-101-1",
        "VlocityDataPackType": "SObject",
        "VlocityRecordSObjectType": "%vlocity_namespace%__DRMapItem__c"
    }
]