[
    {
        "%vlocity_namespace%__AllowIndependentLifeCycle__c": false,
        "%vlocity_namespace%__ChildLineNumber__c": "3",
        "%vlocity_namespace%__ChildProductId__c": {
            "%vlocity_namespace%__GlobalKey__c": "f2bb75bc-ae52-941e-1a2d-e076b6e8accc",
            "VlocityDataPackType": "VlocityLookupMatchingKeyObject",
            "VlocityLookupRecordSourceKey": "Product2/f2bb75bc-ae52-941e-1a2d-e076b6e8accc",
            "VlocityRecordSObjectType": "Product2"
        },
        "%vlocity_namespace%__CollapseHierarchy__c": false,
        "%vlocity_namespace%__GlobalKey__c": "12d42656-7882-2db5-4f53-6a183fb301bc",
        "%vlocity_namespace%__IsOverride__c": true,
        "%vlocity_namespace%__IsRootProductChildItem__c": false,
        "%vlocity_namespace%__IsVirtualItem__c": false,
        "%vlocity_namespace%__MaxQuantity__c": 1,
        "%vlocity_namespace%__MaximumChildItemQuantity__c": 99999,
        "%vlocity_namespace%__MinMaxDefaultQty__c": "1, 1, 1",
        "%vlocity_namespace%__MinQuantity__c": 1,
        "%vlocity_namespace%__MinimumChildItemQuantity__c": 0,
        "%vlocity_namespace%__ParentProductId__c": {
            "%vlocity_namespace%__GlobalKey__c": "7b1c2808-3b4d-9ccc-b024-b5c371a13d75",
            "VlocityDataPackType": "VlocityMatchingKeyObject",
            "VlocityMatchingRecordSourceKey": "Product2/7b1c2808-3b4d-9ccc-b024-b5c371a13d75",
            "VlocityRecordSObjectType": "Product2"
        },
        "%vlocity_namespace%__Quantity__c": 1,
        "%vlocity_namespace%__RelationshipType__c": "",
        "%vlocity_namespace%__SelectionMethodImplementation__c": "",
        "%vlocity_namespace%__SeqNumber__c": 3,
        "Name": "Antivirus Software Override",
        "VlocityDataPackType": "SObject",
        "VlocityRecordSObjectType": "%vlocity_namespace%__ProductChildItem__c",
        "VlocityRecordSourceKey": "%vlocity_namespace%__ProductChildItem__c/12d42656-7882-2db5-4f53-6a183fb301bc"
    },
    {
        "%vlocity_namespace%__AllowIndependentLifeCycle__c": false,
        "%vlocity_namespace%__ChildLineNumber__c": "2",
        "%vlocity_namespace%__ChildProductId__c": {
            "%vlocity_namespace%__GlobalKey__c": "255c83e3-8478-a0db-f5a8-f25dca08b3d6",
            "VlocityDataPackType": "VlocityLookupMatchingKeyObject",
            "VlocityLookupRecordSourceKey": "Product2/255c83e3-8478-a0db-f5a8-f25dca08b3d6",
            "VlocityRecordSObjectType": "Product2"
        },
        "%vlocity_namespace%__CollapseHierarchy__c": false,
        "%vlocity_namespace%__GlobalKey__c": "24d999b3-a4f7-ab5c-c4f6-30067f0e1d0e",
        "%vlocity_namespace%__IsOverride__c": false,
        "%vlocity_namespace%__IsRootProductChildItem__c": false,
        "%vlocity_namespace%__IsVirtualItem__c": false,
        "%vlocity_namespace%__MaxQuantity__c": 1,
        "%vlocity_namespace%__MaximumChildItemQuantity__c": 99999,
        "%vlocity_namespace%__MinMaxDefaultQty__c": "1, 1, 1",
        "%vlocity_namespace%__MinQuantity__c": 1,
        "%vlocity_namespace%__MinimumChildItemQuantity__c": 0,
        "%vlocity_namespace%__ParentProductId__c": {
            "%vlocity_namespace%__GlobalKey__c": "7b1c2808-3b4d-9ccc-b024-b5c371a13d75",
            "VlocityDataPackType": "VlocityMatchingKeyObject",
            "VlocityMatchingRecordSourceKey": "Product2/7b1c2808-3b4d-9ccc-b024-b5c371a13d75",
            "VlocityRecordSObjectType": "Product2"
        },
        "%vlocity_namespace%__Quantity__c": 1,
        "%vlocity_namespace%__RelationshipType__c": "",
        "%vlocity_namespace%__SelectionMethodImplementation__c": "",
        "%vlocity_namespace%__SeqNumber__c": 2,
        "Name": "Firewall Software",
        "VlocityDataPackType": "SObject",
        "VlocityRecordSObjectType": "%vlocity_namespace%__ProductChildItem__c",
        "VlocityRecordSourceKey": "%vlocity_namespace%__ProductChildItem__c/24d999b3-a4f7-ab5c-c4f6-30067f0e1d0e"
    },
    {
        "%vlocity_namespace%__AllowIndependentLifeCycle__c": false,
        "%vlocity_namespace%__ChildLineNumber__c": "1",
        "%vlocity_namespace%__ChildProductId__c": "",
        "%vlocity_namespace%__CollapseHierarchy__c": false,
        "%vlocity_namespace%__GlobalKey__c": "39165ed1-3c1e-c27f-8d10-a438f84b87c7",
        "%vlocity_namespace%__IsOverride__c": false,
        "%vlocity_namespace%__IsRootProductChildItem__c": true,
        "%vlocity_namespace%__IsVirtualItem__c": false,
        "%vlocity_namespace%__MaxQuantity__c": 99999,
        "%vlocity_namespace%__MaximumChildItemQuantity__c": 99999,
        "%vlocity_namespace%__MinMaxDefaultQty__c": "0, 99999, 1",
        "%vlocity_namespace%__MinQuantity__c": 0,
        "%vlocity_namespace%__MinimumChildItemQuantity__c": 0,
        "%vlocity_namespace%__ParentProductId__c": {
            "%vlocity_namespace%__GlobalKey__c": "7b1c2808-3b4d-9ccc-b024-b5c371a13d75",
            "VlocityDataPackType": "VlocityMatchingKeyObject",
            "VlocityMatchingRecordSourceKey": "Product2/7b1c2808-3b4d-9ccc-b024-b5c371a13d75",
            "VlocityRecordSObjectType": "Product2"
        },
        "%vlocity_namespace%__Quantity__c": 1,
        "%vlocity_namespace%__RelationshipType__c": "Child",
        "%vlocity_namespace%__SelectionMethodImplementation__c": "",
        "%vlocity_namespace%__SeqNumber__c": 1,
        "Name": "Root Security Essentials",
        "VlocityDataPackType": "SObject",
        "VlocityRecordSObjectType": "%vlocity_namespace%__ProductChildItem__c",
        "VlocityRecordSourceKey": "%vlocity_namespace%__ProductChildItem__c/39165ed1-3c1e-c27f-8d10-a438f84b87c7"
    },
    {
        "%vlocity_namespace%__AllowIndependentLifeCycle__c": false,
        "%vlocity_namespace%__ChildLineNumber__c": "1",
        "%vlocity_namespace%__ChildProductId__c": {
            "%vlocity_namespace%__GlobalKey__c": "dbbd583a-d09b-b3e0-70ae-a82bd480d059",
            "VlocityDataPackType": "VlocityLookupMatchingKeyObject",
            "VlocityLookupRecordSourceKey": "Product2/dbbd583a-d09b-b3e0-70ae-a82bd480d059",
            "VlocityRecordSObjectType": "Product2"
        },
        "%vlocity_namespace%__CollapseHierarchy__c": false,
        "%vlocity_namespace%__GlobalKey__c": "5b2d2618-a09a-4801-2faa-2cb025812aee",
        "%vlocity_namespace%__IsOverride__c": false,
        "%vlocity_namespace%__IsRootProductChildItem__c": false,
        "%vlocity_namespace%__IsVirtualItem__c": false,
        "%vlocity_namespace%__MaxQuantity__c": 1,
        "%vlocity_namespace%__MaximumChildItemQuantity__c": 99999,
        "%vlocity_namespace%__MinMaxDefaultQty__c": "1, 1, 1",
        "%vlocity_namespace%__MinQuantity__c": 1,
        "%vlocity_namespace%__MinimumChildItemQuantity__c": 0,
        "%vlocity_namespace%__ParentProductId__c": {
            "%vlocity_namespace%__GlobalKey__c": "7b1c2808-3b4d-9ccc-b024-b5c371a13d75",
            "VlocityDataPackType": "VlocityMatchingKeyObject",
            "VlocityMatchingRecordSourceKey": "Product2/7b1c2808-3b4d-9ccc-b024-b5c371a13d75",
            "VlocityRecordSObjectType": "Product2"
        },
        "%vlocity_namespace%__Quantity__c": 1,
        "%vlocity_namespace%__RelationshipType__c": "",
        "%vlocity_namespace%__SelectionMethodImplementation__c": "",
        "%vlocity_namespace%__SeqNumber__c": 1,
        "Name": "Web Safe Software",
        "VlocityDataPackType": "SObject",
        "VlocityRecordSObjectType": "%vlocity_namespace%__ProductChildItem__c",
        "VlocityRecordSourceKey": "%vlocity_namespace%__ProductChildItem__c/5b2d2618-a09a-4801-2faa-2cb025812aee"
    },
    {
        "%vlocity_namespace%__AllowIndependentLifeCycle__c": false,
        "%vlocity_namespace%__ChildLineNumber__c": "1",
        "%vlocity_namespace%__ChildProductId__c": {
            "%vlocity_namespace%__GlobalKey__c": "dbbd583a-d09b-b3e0-70ae-a82bd480d059",
            "VlocityDataPackType": "VlocityLookupMatchingKeyObject",
            "VlocityLookupRecordSourceKey": "Product2/dbbd583a-d09b-b3e0-70ae-a82bd480d059",
            "VlocityRecordSObjectType": "Product2"
        },
        "%vlocity_namespace%__CollapseHierarchy__c": false,
        "%vlocity_namespace%__GlobalKey__c": "6aa183f7-dbe0-0901-d167-e6a906afa0fb",
        "%vlocity_namespace%__IsOverride__c": true,
        "%vlocity_namespace%__IsRootProductChildItem__c": false,
        "%vlocity_namespace%__IsVirtualItem__c": false,
        "%vlocity_namespace%__MaxQuantity__c": 1,
        "%vlocity_namespace%__MaximumChildItemQuantity__c": 99999,
        "%vlocity_namespace%__MinMaxDefaultQty__c": "1, 1, 1",
        "%vlocity_namespace%__MinQuantity__c": 1,
        "%vlocity_namespace%__MinimumChildItemQuantity__c": 0,
        "%vlocity_namespace%__ParentProductId__c": {
            "%vlocity_namespace%__GlobalKey__c": "7b1c2808-3b4d-9ccc-b024-b5c371a13d75",
            "VlocityDataPackType": "VlocityMatchingKeyObject",
            "VlocityMatchingRecordSourceKey": "Product2/7b1c2808-3b4d-9ccc-b024-b5c371a13d75",
            "VlocityRecordSObjectType": "Product2"
        },
        "%vlocity_namespace%__Quantity__c": 1,
        "%vlocity_namespace%__RelationshipType__c": "",
        "%vlocity_namespace%__SelectionMethodImplementation__c": "",
        "%vlocity_namespace%__SeqNumber__c": 1,
        "Name": "Web Safe Software Override",
        "VlocityDataPackType": "SObject",
        "VlocityRecordSObjectType": "%vlocity_namespace%__ProductChildItem__c",
        "VlocityRecordSourceKey": "%vlocity_namespace%__ProductChildItem__c/6aa183f7-dbe0-0901-d167-e6a906afa0fb"
    },
    {
        "%vlocity_namespace%__AllowIndependentLifeCycle__c": false,
        "%vlocity_namespace%__ChildLineNumber__c": "4",
        "%vlocity_namespace%__ChildProductId__c": {
            "%vlocity_namespace%__GlobalKey__c": "30bb7df7-a7b4-397c-fc9a-1e3500f889da",
            "VlocityDataPackType": "VlocityLookupMatchingKeyObject",
            "VlocityLookupRecordSourceKey": "Product2/30bb7df7-a7b4-397c-fc9a-1e3500f889da",
            "VlocityRecordSObjectType": "Product2"
        },
        "%vlocity_namespace%__CollapseHierarchy__c": false,
        "%vlocity_namespace%__GlobalKey__c": "8b417c7e-ccb1-e120-d965-6e9d4f936b35",
        "%vlocity_namespace%__IsOverride__c": false,
        "%vlocity_namespace%__IsRootProductChildItem__c": false,
        "%vlocity_namespace%__IsVirtualItem__c": false,
        "%vlocity_namespace%__MaxQuantity__c": 1,
        "%vlocity_namespace%__MaximumChildItemQuantity__c": 99999,
        "%vlocity_namespace%__MinMaxDefaultQty__c": "1, 1, 1",
        "%vlocity_namespace%__MinQuantity__c": 1,
        "%vlocity_namespace%__MinimumChildItemQuantity__c": 0,
        "%vlocity_namespace%__ParentProductId__c": {
            "%vlocity_namespace%__GlobalKey__c": "7b1c2808-3b4d-9ccc-b024-b5c371a13d75",
            "VlocityDataPackType": "VlocityMatchingKeyObject",
            "VlocityMatchingRecordSourceKey": "Product2/7b1c2808-3b4d-9ccc-b024-b5c371a13d75",
            "VlocityRecordSObjectType": "Product2"
        },
        "%vlocity_namespace%__Quantity__c": 1,
        "%vlocity_namespace%__RelationshipType__c": "",
        "%vlocity_namespace%__SelectionMethodImplementation__c": "",
        "%vlocity_namespace%__SeqNumber__c": 4,
        "Name": "Antimalware Software",
        "VlocityDataPackType": "SObject",
        "VlocityRecordSObjectType": "%vlocity_namespace%__ProductChildItem__c",
        "VlocityRecordSourceKey": "%vlocity_namespace%__ProductChildItem__c/8b417c7e-ccb1-e120-d965-6e9d4f936b35"
    },
    {
        "%vlocity_namespace%__AllowIndependentLifeCycle__c": false,
        "%vlocity_namespace%__ChildLineNumber__c": "4",
        "%vlocity_namespace%__ChildProductId__c": {
            "%vlocity_namespace%__GlobalKey__c": "30bb7df7-a7b4-397c-fc9a-1e3500f889da",
            "VlocityDataPackType": "VlocityLookupMatchingKeyObject",
            "VlocityLookupRecordSourceKey": "Product2/30bb7df7-a7b4-397c-fc9a-1e3500f889da",
            "VlocityRecordSObjectType": "Product2"
        },
        "%vlocity_namespace%__CollapseHierarchy__c": false,
        "%vlocity_namespace%__GlobalKey__c": "e873b42b-bd96-4dad-4eb7-22aa32f0fc4f",
        "%vlocity_namespace%__IsOverride__c": true,
        "%vlocity_namespace%__IsRootProductChildItem__c": false,
        "%vlocity_namespace%__IsVirtualItem__c": false,
        "%vlocity_namespace%__MaxQuantity__c": 1,
        "%vlocity_namespace%__MaximumChildItemQuantity__c": 99999,
        "%vlocity_namespace%__MinMaxDefaultQty__c": "1, 1, 1",
        "%vlocity_namespace%__MinQuantity__c": 1,
        "%vlocity_namespace%__MinimumChildItemQuantity__c": 0,
        "%vlocity_namespace%__ParentProductId__c": {
            "%vlocity_namespace%__GlobalKey__c": "7b1c2808-3b4d-9ccc-b024-b5c371a13d75",
            "VlocityDataPackType": "VlocityMatchingKeyObject",
            "VlocityMatchingRecordSourceKey": "Product2/7b1c2808-3b4d-9ccc-b024-b5c371a13d75",
            "VlocityRecordSObjectType": "Product2"
        },
        "%vlocity_namespace%__Quantity__c": 1,
        "%vlocity_namespace%__RelationshipType__c": "",
        "%vlocity_namespace%__SelectionMethodImplementation__c": "",
        "%vlocity_namespace%__SeqNumber__c": 4,
        "Name": "Antimalware Software Override",
        "VlocityDataPackType": "SObject",
        "VlocityRecordSObjectType": "%vlocity_namespace%__ProductChildItem__c",
        "VlocityRecordSourceKey": "%vlocity_namespace%__ProductChildItem__c/e873b42b-bd96-4dad-4eb7-22aa32f0fc4f"
    },
    {
        "%vlocity_namespace%__AllowIndependentLifeCycle__c": false,
        "%vlocity_namespace%__ChildLineNumber__c": "3",
        "%vlocity_namespace%__ChildProductId__c": {
            "%vlocity_namespace%__GlobalKey__c": "f2bb75bc-ae52-941e-1a2d-e076b6e8accc",
            "VlocityDataPackType": "VlocityLookupMatchingKeyObject",
            "VlocityLookupRecordSourceKey": "Product2/f2bb75bc-ae52-941e-1a2d-e076b6e8accc",
            "VlocityRecordSObjectType": "Product2"
        },
        "%vlocity_namespace%__CollapseHierarchy__c": false,
        "%vlocity_namespace%__GlobalKey__c": "ec328ace-a4d2-d2d1-6560-f86ee37f25bd",
        "%vlocity_namespace%__IsOverride__c": false,
        "%vlocity_namespace%__IsRootProductChildItem__c": false,
        "%vlocity_namespace%__IsVirtualItem__c": false,
        "%vlocity_namespace%__MaxQuantity__c": 1,
        "%vlocity_namespace%__MaximumChildItemQuantity__c": 99999,
        "%vlocity_namespace%__MinMaxDefaultQty__c": "1, 1, 1",
        "%vlocity_namespace%__MinQuantity__c": 1,
        "%vlocity_namespace%__MinimumChildItemQuantity__c": 0,
        "%vlocity_namespace%__ParentProductId__c": {
            "%vlocity_namespace%__GlobalKey__c": "7b1c2808-3b4d-9ccc-b024-b5c371a13d75",
            "VlocityDataPackType": "VlocityMatchingKeyObject",
            "VlocityMatchingRecordSourceKey": "Product2/7b1c2808-3b4d-9ccc-b024-b5c371a13d75",
            "VlocityRecordSObjectType": "Product2"
        },
        "%vlocity_namespace%__Quantity__c": 1,
        "%vlocity_namespace%__RelationshipType__c": "",
        "%vlocity_namespace%__SelectionMethodImplementation__c": "",
        "%vlocity_namespace%__SeqNumber__c": 3,
        "Name": "Antivirus Software",
        "VlocityDataPackType": "SObject",
        "VlocityRecordSObjectType": "%vlocity_namespace%__ProductChildItem__c",
        "VlocityRecordSourceKey": "%vlocity_namespace%__ProductChildItem__c/ec328ace-a4d2-d2d1-6560-f86ee37f25bd"
    },
    {
        "%vlocity_namespace%__AllowIndependentLifeCycle__c": false,
        "%vlocity_namespace%__ChildLineNumber__c": "2",
        "%vlocity_namespace%__ChildProductId__c": {
            "%vlocity_namespace%__GlobalKey__c": "255c83e3-8478-a0db-f5a8-f25dca08b3d6",
            "VlocityDataPackType": "VlocityLookupMatchingKeyObject",
            "VlocityLookupRecordSourceKey": "Product2/255c83e3-8478-a0db-f5a8-f25dca08b3d6",
            "VlocityRecordSObjectType": "Product2"
        },
        "%vlocity_namespace%__CollapseHierarchy__c": false,
        "%vlocity_namespace%__GlobalKey__c": "fe164475-cbdd-5520-6801-86834ae75f90",
        "%vlocity_namespace%__IsOverride__c": true,
        "%vlocity_namespace%__IsRootProductChildItem__c": false,
        "%vlocity_namespace%__IsVirtualItem__c": false,
        "%vlocity_namespace%__MaxQuantity__c": 1,
        "%vlocity_namespace%__MaximumChildItemQuantity__c": 99999,
        "%vlocity_namespace%__MinMaxDefaultQty__c": "1, 1, 1",
        "%vlocity_namespace%__MinQuantity__c": 1,
        "%vlocity_namespace%__MinimumChildItemQuantity__c": 0,
        "%vlocity_namespace%__ParentProductId__c": {
            "%vlocity_namespace%__GlobalKey__c": "7b1c2808-3b4d-9ccc-b024-b5c371a13d75",
            "VlocityDataPackType": "VlocityMatchingKeyObject",
            "VlocityMatchingRecordSourceKey": "Product2/7b1c2808-3b4d-9ccc-b024-b5c371a13d75",
            "VlocityRecordSObjectType": "Product2"
        },
        "%vlocity_namespace%__Quantity__c": 1,
        "%vlocity_namespace%__RelationshipType__c": "",
        "%vlocity_namespace%__SelectionMethodImplementation__c": "",
        "%vlocity_namespace%__SeqNumber__c": 2,
        "Name": "Firewall Software Override",
        "VlocityDataPackType": "SObject",
        "VlocityRecordSObjectType": "%vlocity_namespace%__ProductChildItem__c",
        "VlocityRecordSourceKey": "%vlocity_namespace%__ProductChildItem__c/fe164475-cbdd-5520-6801-86834ae75f90"
    }
]